[
    {
        "similarity_rank": 1,
        "similarity_percentage": 1.0,
        "id": 97,
        "title": "Album 97",
        "imageSrc": "src/backend/database/picture/52.jpg",
        "song": {
            "id": "97_1",
            "file": "Come_Take_My_Hand.mid"
        }
    },
    {
        "similarity_rank": 2,
        "similarity_percentage": 0.904,
        "id": 61,
        "title": "Album 61",
        "imageSrc": "src/backend/database/picture/118.jpg",
        "song": {
            "id": "61_1",
            "file": "Kisses_of_Fire.mid"
        }
    },
    {
        "similarity_rank": 3,
        "similarity_percentage": 0.8455,
        "id": 127,
        "title": "Album 127",
        "imageSrc": "src/backend/database/picture/99.jpg",
        "song": {
            "id": "127_1",
            "file": "Dance_While_the_Music_Still_Goes_on_.3.mid"
        }
    },
    {
        "similarity_rank": 4,
        "similarity_percentage": 0.8008,
        "id": 39,
        "title": "Album 39",
        "imageSrc": "src/backend/database/picture/63.jpg",
        "song": {
            "id": "39_1",
            "file": "Money,_Money,_Money.7.mid"
        }
    },
    {
        "similarity_rank": 5,
        "similarity_percentage": 0.7986,
        "id": 107,
        "title": "Album 107",
        "imageSrc": "src/backend/database/picture/19.jpg",
        "song": {
            "id": "107_1",
            "file": "Knowing_Me,_Knowing_You.9.mid"
        }
    },
    {
        "similarity_rank": 6,
        "similarity_percentage": 0.771,
        "id": 94,
        "title": "Album 94",
        "imageSrc": "src/backend/database/picture/73.jpg",
        "song": {
            "id": "94_2",
            "file": "Dreams.1.mid"
        }
    }
]